[
  {
    "ticker": "SNOW",
    "action": "STRONG_SELL",
    "entry_price": 152.45,
    "stop_loss": 160.0725,
    "take_profit": 129.58249999999998,
    "score": -0.5547217206572076,
    "confidence": 0.7254179636059189,
    "universe": "NASDAQ100",
    "issued_at": "2026-05-11T08:40:32.481555",
    "horizon_days": 1,
    "horizon_hours": 24,
    "status": "expired",
    "exit_price": 151.97999572753906,
    "exit_date": "2026-05-12",
    "pnl_pct": 0.00308300605090801,
    "max_favorable": 0.006231551328304288,
    "max_adverse": 0.00308300605090801
  },
  {
    "ticker": "NFLX",
    "action": "STRONG_SELL",
    "entry_price": 87.477,
    "stop_loss": 88.99842579214913,
    "take_profit": 83.21700778198243,
    "score": -0.4629417518546451,
    "confidence": 0.7249476847060776,
    "universe": "NASDAQ100",
    "issued_at": "2026-05-11T08:40:32.481581",
    "horizon_days": 1,
    "horizon_hours": 24,
    "status": "expired",
    "exit_price": 87.66000366210938,
    "exit_date": "2026-05-12",
    "pnl_pct": -0.002092020326592946,
    "max_favorable": 0.023171840046615867,
    "max_adverse": -0.002092020326592946
  },
  {
    "ticker": "PYPL",
    "action": "STRONG_SELL",
    "entry_price": 45.37,
    "stop_loss": 46.5946424811227,
    "take_profit": 41.94100105285644,
    "score": -0.43168850817760585,
    "confidence": 0.7474198023441335,
    "universe": "NASDAQ100",
    "issued_at": "2026-05-11T08:40:32.481584",
    "horizon_days": 1,
    "horizon_hours": 24,
    "status": "expired",
    "exit_price": 45.439998626708984,
    "exit_date": "2026-05-12",
    "pnl_pct": -0.0015428394690100713,
    "max_favorable": 0.006612305602287386,
    "max_adverse": -0.0015428394690100713
  },
  {
    "ticker": "DOCU",
    "action": "STRONG_SELL",
    "entry_price": 47.9,
    "stop_loss": 49.7528562273298,
    "take_profit": 42.71200256347656,
    "score": -0.45504773790484193,
    "confidence": 0.7064823090694274,
    "universe": "NASDAQ100",
    "issued_at": "2026-05-11T08:40:32.481587",
    "horizon_days": 1,
    "horizon_hours": 24,
    "status": "expired",
    "exit_price": 45.18000030517578,
    "exit_date": "2026-05-12",
    "pnl_pct": 0.05678496231365798,
    "max_favorable": 0.05678496231365798,
    "max_adverse": 0.05031311735977457
  },
  {
    "ticker": "ON",
    "action": "BUY",
    "entry_price": 103.197,
    "stop_loss": 98.03715,
    "take_profit": 118.67655,
    "score": 0.39899176545267295,
    "confidence": 0.8,
    "universe": "NASDAQ100",
    "issued_at": "2026-05-11T08:40:32.481590",
    "horizon_days": 1,
    "horizon_hours": 24,
    "status": "expired",
    "exit_price": 104.11000061035156,
    "exit_date": "2026-05-12",
    "pnl_pct": 0.00884716232401678,
    "max_favorable": 0.03917747476932012,
    "max_adverse": 0.00884716232401678
  },
  {
    "ticker": "TMUS",
    "action": "STRONG_SELL",
    "entry_price": 193.63,
    "stop_loss": 198.88749914986747,
    "take_profit": 178.90900238037108,
    "score": -0.4577678510766972,
    "confidence": 0.6942258073299287,
    "universe": "NASDAQ100",
    "issued_at": "2026-05-11T08:40:32.481592",
    "horizon_days": 1,
    "horizon_hours": 24,
    "status": "expired",
    "exit_price": 193.3000030517578,
    "exit_date": "2026-05-12",
    "pnl_pct": 0.0017042656005896966,
    "max_favorable": 0.014357247825669424,
    "max_adverse": 0.0017042656005896966
  },
  {
    "ticker": "PAYX",
    "action": "STRONG_SELL",
    "entry_price": 93.93,
    "stop_loss": 95.65285815647671,
    "take_profit": 89.10599716186525,
    "score": -0.4395406827565042,
    "confidence": 0.7208755077240652,
    "universe": "NASDAQ100",
    "issued_at": "2026-05-11T08:40:32.481595",
    "horizon_days": 1,
    "horizon_hours": 24,
    "status": "expired",
    "exit_price": 93.70999908447266,
    "exit_date": "2026-05-12",
    "pnl_pct": 0.0023421794477520553,
    "max_favorable": 0.0023421794477520553,
    "max_adverse": 0.0005323405363785593
  },
  {
    "ticker": "VRSK",
    "action": "STRONG_SELL",
    "entry_price": 171.87,
    "stop_loss": 177.34285897391183,
    "take_profit": 156.54599487304688,
    "score": -0.46100517742607416,
    "confidence": 0.6845287707601692,
    "universe": "NASDAQ100",
    "issued_at": "2026-05-11T08:40:32.481598",
    "horizon_days": 1,
    "horizon_hours": 24,
    "status": "expired",
    "exit_price": 166.32000732421875,
    "exit_date": "2026-05-12",
    "pnl_pct": 0.03229180587526185,
    "max_favorable": 0.03229180587526185,
    "max_adverse": 0.01920051594682757
  },
  {
    "ticker": "NFLX",
    "action": "STRONG_SELL",
    "entry_price": 87.265,
    "stop_loss": 88.573975,
    "take_profit": 83.60350860595703,
    "score": -0.46294879512458936,
    "confidence": 0.7273483056889934,
    "universe": "NASDAQ100",
    "issued_at": "2026-05-11T14:30:04.863444",
    "horizon_days": 1,
    "horizon_hours": 24,
    "status": "expired",
    "exit_price": 87.66000366210938,
    "exit_date": "2026-05-12",
    "pnl_pct": -0.004526484410810456,
    "max_favorable": 0.020798751524182812,
    "max_adverse": -0.004526484410810456
  },
  {
    "ticker": "TMUS",
    "action": "STRONG_SELL",
    "entry_price": 193.11,
    "stop_loss": 198.10499947684153,
    "take_profit": 179.12400146484376,
    "score": -0.46265770824155145,
    "confidence": 0.6926033748586498,
    "universe": "NASDAQ100",
    "issued_at": "2026-05-11T14:30:04.863468",
    "horizon_days": 1,
    "horizon_hours": 24,
    "status": "expired",
    "exit_price": 193.3000030517578,
    "exit_date": "2026-05-12",
    "pnl_pct": -0.0009839109924799278,
    "max_favorable": 0.011703142750165131,
    "max_adverse": -0.0009839109924799278
  },
  {
    "ticker": "ON",
    "action": "STRONG_BUY",
    "entry_price": 103.82,
    "stop_loss": 98.62899999999999,
    "take_profit": 119.39299999999999,
    "score": 0.400095822436239,
    "confidence": 0.8,
    "universe": "NASDAQ100",
    "issued_at": "2026-05-11T14:30:04.863473",
    "horizon_days": 1,
    "horizon_hours": 24,
    "status": "expired",
    "exit_price": 104.11000061035156,
    "exit_date": "2026-05-12",
    "pnl_pct": 0.0027933019683256534,
    "max_favorable": 0.032941609167497,
    "max_adverse": 0.0027933019683256534
  },
  {
    "ticker": "VRSK",
    "action": "STRONG_SELL",
    "entry_price": 171.215,
    "stop_loss": 176.5282155282157,
    "take_profit": 156.33799652099611,
    "score": -0.4653271515136889,
    "confidence": 0.6845607799848844,
    "universe": "NASDAQ100",
    "issued_at": "2026-05-11T14:30:04.863477",
    "horizon_days": 1,
    "horizon_hours": 24,
    "status": "expired",
    "exit_price": 166.32000732421875,
    "exit_date": "2026-05-12",
    "pnl_pct": 0.028589741995626864,
    "max_favorable": 0.028589741995626864,
    "max_adverse": 0.01544837003639432
  },
  {
    "ticker": "PAYX",
    "action": "STRONG_SELL",
    "entry_price": 93.41,
    "stop_loss": 95.12642902919224,
    "take_profit": 88.60399871826172,
    "score": -0.4349999729707388,
    "confidence": 0.7204023897319132,
    "universe": "NASDAQ100",
    "issued_at": "2026-05-11T14:30:04.863480",
    "horizon_days": 1,
    "horizon_hours": 24,
    "status": "expired",
    "exit_price": 93.70999908447266,
    "exit_date": "2026-05-12",
    "pnl_pct": -0.0032116377740355386,
    "max_favorable": -0.0032116377740355386,
    "max_adverse": -0.005031551797644494
  },
  {
    "ticker": "MSFT",
    "action": "STRONG_SELL",
    "entry_price": 410.735,
    "stop_loss": 420.381607535226,
    "take_profit": 383.7244989013672,
    "score": -0.4053142818565236,
    "confidence": 0.698141226012956,
    "universe": "NASDAQ100",
    "issued_at": "2026-05-11T14:30:04.863484",
    "horizon_days": 1,
    "horizon_hours": 24,
    "status": "expired",
    "exit_price": 407.7699890136719,
    "exit_date": "2026-05-12",
    "pnl_pct": 0.007218793105842304,
    "max_favorable": 0.007218793105842304,
    "max_adverse": -0.004686729064017825
  },
  {
    "ticker": "ON",
    "action": "BUY",
    "entry_price": 105.29,
    "stop_loss": 100.02550000000001,
    "take_profit": 121.0835,
    "score": 0.38827749894352415,
    "confidence": 0.8,
    "universe": "NASDAQ100",
    "issued_at": "2026-05-11T16:03:50.525627",
    "horizon_days": 1,
    "horizon_hours": 24,
    "status": "expired",
    "exit_price": 104.11000061035156,
    "exit_date": "2026-05-12",
    "pnl_pct": -0.011207136381882836,
    "max_favorable": 0.01852025704026522,
    "max_adverse": -0.011207136381882836
  },
  {
    "ticker": "MRVL",
    "action": "BUY",
    "entry_price": 172.445,
    "stop_loss": 163.82274999999998,
    "take_profit": 198.31175,
    "score": 0.38149514926216493,
    "confidence": 0.8,
    "universe": "NASDAQ100",
    "issued_at": "2026-05-11T16:03:50.525654",
    "horizon_days": 1,
    "horizon_hours": 24,
    "status": "expired",
    "exit_price": 164.5,
    "exit_date": "2026-05-12",
    "pnl_pct": -0.046072660848386404,
    "max_favorable": -0.009307336612307508,
    "max_adverse": -0.046072660848386404
  },
  {
    "ticker": "KDP",
    "action": "SELL",
    "entry_price": 28.615,
    "stop_loss": 29.3226781136649,
    "take_profit": 26.63350128173828,
    "score": -0.3874041434430815,
    "confidence": 0.7049879576221506,
    "universe": "NASDAQ100",
    "issued_at": "2026-05-11T16:03:50.525658",
    "horizon_days": 1,
    "horizon_hours": 24,
    "status": "expired",
    "exit_price": 29.170000076293945,
    "exit_date": "2026-05-12",
    "pnl_pct": -0.019395424647700398,
    "max_favorable": -0.0033199051012635966,
    "max_adverse": -0.019395424647700398
  },
  {
    "ticker": "KHC",
    "action": "STRONG_SELL",
    "entry_price": 23.165,
    "stop_loss": 23.554463697160994,
    "take_profit": 22.07450164794922,
    "score": -0.4098748388352814,
    "confidence": 0.722942295734369,
    "universe": "NASDAQ100",
    "issued_at": "2026-05-11T17:22:10.657118",
    "horizon_days": 1,
    "horizon_hours": 24,
    "status": "expired",
    "exit_price": 23.3700008392334,
    "exit_date": "2026-05-12",
    "pnl_pct": -0.008849593750632389,
    "max_favorable": -0.004101024341974392,
    "max_adverse": -0.008849593750632389
  },
  {
    "ticker": "PINS",
    "action": "SELL",
    "entry_price": 20.545,
    "stop_loss": 21.57225,
    "take_profit": 17.667000122070313,
    "score": -0.3939353775271726,
    "confidence": 0.7075743119071611,
    "universe": "NASDAQ100",
    "issued_at": "2026-05-11T17:22:10.657144",
    "horizon_days": 1,
    "horizon_hours": 24,
    "status": "expired",
    "exit_price": 20.559999465942383,
    "exit_date": "2026-05-12",
    "pnl_pct": -0.0007300786538029255,
    "max_favorable": -0.0007300786538029255,
    "max_adverse": -0.010464844433284702
  },
  {
    "ticker": "TEAM",
    "action": "STRONG_SELL",
    "entry_price": 87.31,
    "stop_loss": 91.6755,
    "take_profit": 74.2135,
    "score": -0.520283307879772,
    "confidence": 0.740897664887373,
    "universe": "NASDAQ100",
    "issued_at": "2026-05-11T20:09:28.613872",
    "horizon_days": 1,
    "horizon_hours": 24,
    "status": "expired",
    "exit_price": 85.0,
    "exit_date": "2026-05-12",
    "pnl_pct": 0.026457450463864416,
    "max_favorable": 0.026457450463864416,
    "max_adverse": 2.7962504321082772e-08
  },
  {
    "ticker": "MRVL",
    "action": "STRONG_BUY",
    "entry_price": 170.84,
    "stop_loss": 162.298,
    "take_profit": 196.466,
    "score": 0.4036457604069005,
    "confidence": 0.8,
    "universe": "NASDAQ100",
    "issued_at": "2026-05-11T20:09:28.613901",
    "horizon_days": 1,
    "horizon_hours": 24,
    "status": "expired",
    "exit_price": 164.5,
    "exit_date": "2026-05-12",
    "pnl_pct": -0.03711074689768206,
    "max_favorable": -2.1435901301864932e-08,
    "max_adverse": -0.03711074689768206
  }
]