[
  {
    "ticker": "DOCU",
    "action": "STRONG_SELL",
    "entry_price": 46.9,
    "stop_loss": 48.75714176722935,
    "take_profit": 41.70000305175781,
    "score": -0.46817403667725505,
    "confidence": 0.7007693145009846,
    "universe": "NASDAQ100",
    "issued_at": "2026-05-06T15:49:46.761906",
    "horizon_days": 1,
    "horizon_hours": 24,
    "status": "open",
    "exit_price": null,
    "exit_date": null,
    "pnl_pct": null,
    "max_favorable": null,
    "max_adverse": null
  },
  {
    "ticker": "PAYX",
    "action": "STRONG_SELL",
    "entry_price": 91.51,
    "stop_loss": 93.01107084001814,
    "take_profit": 87.30700164794922,
    "score": -0.46345469744621604,
    "confidence": 0.7107690117052896,
    "universe": "NASDAQ100",
    "issued_at": "2026-05-06T17:06:06.603590",
    "horizon_days": 1,
    "horizon_hours": 24,
    "status": "open",
    "exit_price": null,
    "exit_date": null,
    "pnl_pct": null,
    "max_favorable": null,
    "max_adverse": null
  },
  {
    "ticker": "PYPL",
    "action": "STRONG_SELL",
    "entry_price": 46.15,
    "stop_loss": 47.46249918256487,
    "take_profit": 42.47500228881836,
    "score": -0.43764543364884634,
    "confidence": 0.7486797877478314,
    "universe": "NASDAQ100",
    "issued_at": "2026-05-06T17:06:06.603616",
    "horizon_days": 1,
    "horizon_hours": 24,
    "status": "open",
    "exit_price": null,
    "exit_date": null,
    "pnl_pct": null,
    "max_favorable": null,
    "max_adverse": null
  },
  {
    "ticker": "NFLX",
    "action": "STRONG_SELL",
    "entry_price": 87.93,
    "stop_loss": 90.72105867658344,
    "take_profit": 80.11503570556641,
    "score": -0.42126549832887994,
    "confidence": 0.737051592261625,
    "universe": "NASDAQ100",
    "issued_at": "2026-05-06T17:06:06.603620",
    "horizon_days": 1,
    "horizon_hours": 24,
    "status": "open",
    "exit_price": null,
    "exit_date": null,
    "pnl_pct": null,
    "max_favorable": null,
    "max_adverse": null
  },
  {
    "ticker": "TMUS",
    "action": "STRONG_SELL",
    "entry_price": 192.975,
    "stop_loss": 198.21267961774552,
    "take_profit": 178.3094970703125,
    "score": -0.452035004474763,
    "confidence": 0.6840520011151574,
    "universe": "NASDAQ100",
    "issued_at": "2026-05-06T17:06:06.603624",
    "horizon_days": 1,
    "horizon_hours": 24,
    "status": "open",
    "exit_price": null,
    "exit_date": null,
    "pnl_pct": null,
    "max_favorable": null,
    "max_adverse": null
  },
  {
    "ticker": "PLTR",
    "action": "STRONG_SELL",
    "entry_price": 133.1116,
    "stop_loss": 139.76718,
    "take_profit": 113.32360561523438,
    "score": -0.41837229161125766,
    "confidence": 0.7352188345581566,
    "universe": "NASDAQ100",
    "issued_at": "2026-05-06T17:06:06.603626",
    "horizon_days": 1,
    "horizon_hours": 24,
    "status": "open",
    "exit_price": null,
    "exit_date": null,
    "pnl_pct": null,
    "max_favorable": null,
    "max_adverse": null
  },
  {
    "ticker": "IDXX",
    "action": "STRONG_SELL",
    "entry_price": 577.47,
    "stop_loss": 591.7510821533203,
    "take_profit": 537.4829699707032,
    "score": -0.5361516107323937,
    "confidence": 0.8027112886605282,
    "universe": "NASDAQ100",
    "issued_at": "2026-05-06T18:29:36.754712",
    "horizon_days": 1,
    "horizon_hours": 24,
    "status": "open",
    "exit_price": null,
    "exit_date": null,
    "pnl_pct": null,
    "max_favorable": null,
    "max_adverse": null
  },
  {
    "ticker": "ADBE",
    "action": "STRONG_SELL",
    "entry_price": 251.35,
    "stop_loss": 261.1021493094308,
    "take_profit": 224.04398193359376,
    "score": -0.4863332063228365,
    "confidence": 0.8098708489574709,
    "universe": "NASDAQ100",
    "issued_at": "2026-05-06T18:29:36.754737",
    "horizon_days": 1,
    "horizon_hours": 24,
    "status": "open",
    "exit_price": null,
    "exit_date": null,
    "pnl_pct": null,
    "max_favorable": null,
    "max_adverse": null
  },
  {
    "ticker": "DKNG",
    "action": "STRONG_SELL",
    "entry_price": 23.92,
    "stop_loss": 24.517857339041576,
    "take_profit": 22.245999450683595,
    "score": -0.49372823836624125,
    "confidence": 0.7047288996507708,
    "universe": "NASDAQ100",
    "issued_at": "2026-05-06T20:07:34.981406",
    "horizon_days": 1,
    "horizon_hours": 24,
    "status": "open",
    "exit_price": null,
    "exit_date": null,
    "pnl_pct": null,
    "max_favorable": null,
    "max_adverse": null
  },
  {
    "ticker": "MSFT",
    "action": "STRONG_SELL",
    "entry_price": 413.866,
    "stop_loss": 423.1280729718889,
    "take_profit": 387.9321956787109,
    "score": -0.42211154016626057,
    "confidence": 0.7005989043149585,
    "universe": "NASDAQ100",
    "issued_at": "2026-05-06T20:07:34.981433",
    "horizon_days": 1,
    "horizon_hours": 24,
    "status": "open",
    "exit_price": null,
    "exit_date": null,
    "pnl_pct": null,
    "max_favorable": null,
    "max_adverse": null
  }
]